conversational_graph/__init__.py
conversational_graph/factory.py
conversational_graph_dev-0.0.18.dist-info/METADATA
conversational_graph_dev-0.0.18.dist-info/WHEEL
conversational_graph_dev-0.0.18.dist-info/top_level.txt
conversational_graph_dev-0.0.18.dist-info/RECORD
