Metadata-Version: 2.4
Name: conversational-graph-dev
Version: 0.0.18
Summary: Conversational graph package
Author: Videosdk
Requires-Python: >=3.9
